setup.py
arith/Arith.py
arith/__init__.py
arith/fib.py
arith/palindrome.py
arith.egg-info/PKG-INFO
arith.egg-info/SOURCES.txt
arith.egg-info/dependency_links.txt
arith.egg-info/top_level.txt