Metadata-Version: 1.0
Name: arith
Version: 1.0.0
Summary: Useful towel-related stuff
Home-page: http://pypi.python.org/pypi/MyApplication_v010/
Author: ramya
Author-email: munja.ramya@gmail.com
License: UNKNOWN
Platform: UNKNOWN
